hieroskopia/__init__.py
hieroskopia/date_analyser.py
hieroskopia/numeric_analyser.py
hieroskopia/tests/__init__.py
hieroskopia/tests/test_date_analyser.py
hieroskopia/tests/test_numeric_analyser.py
hieroskopia/utils/__init__.py
hieroskopia/utils/evaluator.py
hieroskopia-0.1.30.dist-info/AUTHORS
hieroskopia-0.1.30.dist-info/LICENSE
hieroskopia-0.1.30.dist-info/METADATA
hieroskopia-0.1.30.dist-info/WHEEL
hieroskopia-0.1.30.dist-info/top_level.txt
hieroskopia-0.1.30.dist-info/RECORD
