Metadata-Version: 2.1
Name: hieroskopia
Version: 0.1.30
Summary: The hiereskopia package is a library to infer properties like date formats or numeric separators in pandas series of type object or string.
Home-page: https://github.com/simetrikinc/hieroskopia
Author: Simetrik Inc
Author-email: opensource@simetrik.com
License: UNKNOWN
Platform: UNKNOWN
Classifier: Programming Language :: Python :: 3
Classifier: License :: OSI Approved :: MIT License
Classifier: Operating System :: OS Independent
Requires-Python: >=3.6
